{
  "layouts": [
    {
      "enable": "true",
      "zone": 1,
      "style": "style0",
      "decorators":
      [
        {
          "id": 1
        },
        {
          "id": 2
        }
      ],
      "layoutItems":
      [
        {
          "id": 1
        },
        {
          "id": 2
        }
      ],
      "nextShapes":
      [
        "HallStraight"
      ]
    },
    {
      "enable": "true",
      "zone": 1,
      "style": "style0",
      "nextShapes":
      [
        "HallStraight"
      ]
    },
    {
      "enable": "true",
      "zone": 1,
      "style": "style1",
      "nextShapes":
      [
        "HallStraight"
      ]
    },
    {
      "enable": "true",
      "zone": 1,
      "style": "style2",
      "nextShapes": 
      [
        "HallStraight"
      ]
    },
    {
      "enable": "true",
      "zone": 1,
      "style": "style3",
      "nextShapes":
      [
        "HallStraight"
      ]
    },
    {
      "enable": "true",
      "zone": 1,
      "style": "style4",
      "nextShapes":
      [
        "HallStraight"
      ]
    },
    {
      "enable": "true",
      "zone": 1,
      "style": "style2",
      "nextShapes":
      [
        "HallStraight"
      ]
    },
    {
      "enable": "true",
      "zone": 4,
      "style": "style2",
      "nextShapes": null
    }
  ]
}